{
  "users": [
    {
      "id": 4,
      "name": "updated user",
      "email": "updateuser@gmail.com",
      "phone": "0987654321",
      "address": {
        "street": "456 Main St",
        "city": "New York",
        "state": "NY",
        "zip": "10001"
      }
    },
    {
      "name": "Terry",
      "email": "atuny0@sohu.com",
      "phone": "+63 791 675 8914",
      "id": 8
    },
    {
      "name": "Sheldon",
      "email": "hbingley1@plala.or.jp",
      "phone": "+7 813 117 7139",
      "id": 9
    },
    {
      "name": "Terrill updated",
      "email": "terrillupdated@gmail.com",
      "phone": "+63 739 292 7942",
      "id": 10
    },
    {
      "name": "John Doe",
      "email": "johndoe@gmail.com",
      "phone": "+1 23423423 55",
      "id": 11
    },
    {
      "name": "Create test user",
      "email": "create.test.user@test.com",
      "phone": "3473678263",
      "id": 14
    },
    {
      "name": "Leanne Graham",
      "email": "sincere@april.biz",
      "phone": "1-770-736-8031",
      "id": 15
    },
    {
      "name": "Ervin Howell",
      "email": "Shanna@melissa.tv",
      "phone": "010-692-6593",
      "id": 16
    },
    {
      "name": "Chelsey Dietrich",
      "email": "Lucio_Hettinger@annie.ca",
      "phone": "(254) 954-1289",
      "id": 17
    },
    {
      "name": "test updated",
      "email": "testupdated@gmail.com",
      "phone": "78368759809",
      "id": 18
    }
  ]
}